aipod/__init__.py
aipod/__version__.py
aipod/model.py
aipod/package.py
aipod/pool.py
aipod/trainlog.py
aipod/rpc/__init__.py
aipod/rpc/client.py
aipod/rpc/server.py
aipod/rpc/proto/__init__.py
aipod/rpc/proto/ai_pb2.py
aipod/rpc/proto/ai_pb2_grpc.py
aipod-1.0.0.dist-info/LICENSE
aipod-1.0.0.dist-info/METADATA
aipod-1.0.0.dist-info/WHEEL
aipod-1.0.0.dist-info/top_level.txt
aipod-1.0.0.dist-info/RECORD
