Metadata-Version: 2.1
Name: aipod
Version: 1.0.0
Summary: A framework for packaging the models provided by the AI.
Home-page: https://github.com/PaodingAI/aipod
Author: PaodingAI
Author-email: opensource@paodingai.com
License: MIT
Platform: UNKNOWN
Classifier: License :: OSI Approved :: MIT License
Classifier: Programming Language :: Python
Classifier: Programming Language :: Python :: 3
Classifier: Programming Language :: Python :: 3.6
Classifier: Programming Language :: Python :: Implementation :: CPython
Classifier: Programming Language :: Python :: Implementation :: PyPy
Requires-Python: >=3.6.0
Requires-Dist: grpcio-tools (<2.0.0,>=1.32.0)
